[
  {
    "id": "uzun-ince-bir-yoldayim",
    "title": "Uzun İnce Bir Yoldayım",
    "artist": "Aşık Veysel",
    "expected_bpm": 72,
    "description": "Hüseyni makamı. Kısa sap Re-Sol-La akort düzeni.",
    "tuning": "kisa_sap_re_sol_la",
    "tuning_offset_semitones": 0,
    "notes": [
      { "time": 0.0,  "note": "D4",  "duration": 0.5,  "solfege": "do" },
      { "time": 0.5,  "note": "E4",  "duration": 0.75, "solfege": "re" },
      { "time": 1.25, "note": "E4",  "duration": 0.75, "solfege": "re" },
      { "time": 2.0,  "note": "D4",  "duration": 0.5,  "solfege": "do" },
      { "time": 2.5,  "note": "C5",  "duration": 0.5,  "solfege": "si" },
      { "time": 3.0,  "note": "B4",  "duration": 0.5,  "solfege": "la" },
      { "time": 3.5,  "note": "D4",  "duration": 0.5,  "solfege": "do" },
      { "time": 4.0,  "note": "C5",  "duration": 0.75, "solfege": "si" },
      { "time": 4.75, "note": "B4",  "duration": 0.5,  "solfege": "la" },
      { "time": 5.25, "note": "B4",  "duration": 0.5,  "solfege": "la" },
      { "time": 5.75, "note": "B4",  "duration": 1.0,  "solfege": "la" },
      { "time": 6.75, "note": "F#4", "duration": 0.5,  "solfege": "mi" },
      { "time": 7.25, "note": "E4",  "duration": 0.5,  "solfege": "re" },
      { "time": 7.75, "note": "F#4", "duration": 0.5,  "solfege": "mi" },
      { "time": 8.25, "note": "D4",  "duration": 0.5,  "solfege": "do" },
      { "time": 8.75, "note": "E4",  "duration": 0.75, "solfege": "re" },
      { "time": 9.5,  "note": "D4",  "duration": 0.5,  "solfege": "do" },
      { "time": 10.0, "note": "C5",  "duration": 0.5,  "solfege": "si" },
      { "time": 10.5, "note": "B4",  "duration": 0.5,  "solfege": "la" },
      { "time": 11.0, "note": "D4",  "duration": 0.5,  "solfege": "do" },
      { "time": 11.5, "note": "C5",  "duration": 0.75, "solfege": "si" },
      { "time": 12.25,"note": "B4",  "duration": 0.5,  "solfege": "la" },
      { "time": 12.75,"note": "B4",  "duration": 0.5,  "solfege": "la" },
      { "time": 13.25,"note": "B4",  "duration": 1.0,  "solfege": "la" },
      { "time": 14.25,"note": "D4",  "duration": 0.5,  "solfege": "do" },
      { "time": 14.75,"note": "E4",  "duration": 0.75, "solfege": "re" },
      { "time": 15.5, "note": "E4",  "duration": 0.75, "solfege": "re" },
      { "time": 16.25,"note": "D4",  "duration": 0.5,  "solfege": "do" },
      { "time": 16.75,"note": "C5",  "duration": 0.5,  "solfege": "si" },
      { "time": 17.25,"note": "B4",  "duration": 0.5,  "solfege": "la" },
      { "time": 17.75,"note": "D4",  "duration": 0.5,  "solfege": "do" },
      { "time": 18.25,"note": "C5",  "duration": 0.75, "solfege": "si" },
      { "time": 19.0, "note": "B4",  "duration": 0.5,  "solfege": "la" },
      { "time": 19.5, "note": "B4",  "duration": 0.5,  "solfege": "la" },
      { "time": 20.0, "note": "B4",  "duration": 1.0,  "solfege": "la" },
      { "time": 21.0, "note": "F#4", "duration": 0.5,  "solfege": "mi" },
      { "time": 21.5, "note": "E4",  "duration": 0.5,  "solfege": "re" },
      { "time": 22.0, "note": "F#4", "duration": 0.5,  "solfege": "mi" },
      { "time": 22.5, "note": "D4",  "duration": 0.5,  "solfege": "do" },
      { "time": 23.0, "note": "E4",  "duration": 0.75, "solfege": "re" },
      { "time": 23.75,"note": "D4",  "duration": 0.5,  "solfege": "do" },
      { "time": 24.25,"note": "C5",  "duration": 0.5,  "solfege": "si" },
      { "time": 24.75,"note": "B4",  "duration": 0.5,  "solfege": "la" },
      { "time": 25.25,"note": "D4",  "duration": 0.5,  "solfege": "do" },
      { "time": 25.75,"note": "C5",  "duration": 0.75, "solfege": "si" },
      { "time": 26.5, "note": "B4",  "duration": 0.5,  "solfege": "la" },
      { "time": 27.0, "note": "B4",  "duration": 0.5,  "solfege": "la" },
      { "time": 27.5, "note": "B4",  "duration": 1.0,  "solfege": "la" },
      { "time": 28.5, "note": "G#4", "duration": 0.5,  "solfege": "fa#" },
      { "time": 29.0, "note": "A4",  "duration": 0.5,  "solfege": "sol" },
      { "time": 29.5, "note": "A4",  "duration": 0.5,  "solfege": "sol" },
      { "time": 30.0, "note": "A4",  "duration": 0.75, "solfege": "sol" },
      { "time": 30.75,"note": "A4",  "duration": 0.5,  "solfege": "sol" },
      { "time": 31.25,"note": "G#4", "duration": 0.75, "solfege": "fa#" },
      { "time": 32.0, "note": "F#4", "duration": 0.5,  "solfege": "mi" },
      { "time": 32.5, "note": "A4",  "duration": 0.75, "solfege": "sol" },
      { "time": 33.25,"note": "G#4", "duration": 1.0,  "solfege": "fa#" },
      { "time": 34.25,"note": "A4",  "duration": 0.5,  "solfege": "sol" },
      { "time": 34.75,"note": "F#4", "duration": 0.75, "solfege": "mi" },
      { "time": 35.5, "note": "E4",  "duration": 0.5,  "solfege": "re" },
      { "time": 36.0, "note": "F#4", "duration": 0.5,  "solfege": "mi" },
      { "time": 36.5, "note": "F#4", "duration": 0.5,  "solfege": "mi" },
      { "time": 37.0, "note": "F#4", "duration": 0.5,  "solfege": "mi" },
      { "time": 37.5, "note": "E4",  "duration": 0.5,  "solfege": "re" },
      { "time": 38.0, "note": "D4",  "duration": 0.5,  "solfege": "do" },
      { "time": 38.5, "note": "F#4", "duration": 0.5,  "solfege": "mi" },
      { "time": 39.0, "note": "E4",  "duration": 0.75, "solfege": "re" },
      { "time": 39.75,"note": "E4",  "duration": 0.5,  "solfege": "re" },
      { "time": 40.25,"note": "D4",  "duration": 0.5,  "solfege": "do" },
      { "time": 40.75,"note": "C5",  "duration": 0.5,  "solfege": "si" },
      { "time": 41.25,"note": "B4",  "duration": 0.5,  "solfege": "la" },
      { "time": 41.75,"note": "E4",  "duration": 0.5,  "solfege": "re" },
      { "time": 42.25,"note": "C5",  "duration": 0.5,  "solfege": "si" },
      { "time": 42.75,"note": "D4",  "duration": 0.75, "solfege": "do" },
      { "time": 43.5, "note": "D4",  "duration": 0.5,  "solfege": "do" },
      { "time": 44.0, "note": "C5",  "duration": 0.5,  "solfege": "si" },
      { "time": 44.5, "note": "B4",  "duration": 0.5,  "solfege": "la" },
      { "time": 45.0, "note": "D4",  "duration": 0.5,  "solfege": "do" },
      { "time": 45.5, "note": "C5",  "duration": 0.75, "solfege": "si" },
      { "time": 46.25,"note": "C5",  "duration": 0.5,  "solfege": "si" },
      { "time": 46.75,"note": "B4",  "duration": 0.75, "solfege": "la" },
      { "time": 47.5, "note": "A4",  "duration": 0.5,  "solfege": "sol" },
      { "time": 48.0, "note": "C5",  "duration": 0.5,  "solfege": "si" },
      { "time": 48.5, "note": "B4",  "duration": 0.5,  "solfege": "la" },
      { "time": 49.0, "note": "B4",  "duration": 2.5,  "solfege": "la" }
    ],
    "makam": "huseyni",
    "total_duration_sec": 51.5
  },
  {
    "id": "urfanin-etraf",
    "title": "Urfanın Etrafı Dumanlı Dağlar",
    "artist": "Anonim",
    "expected_bpm": 85,
    "description": "Hicaz makamı. Kısa sap Re-Sol-La akort düzeni.",
    "tuning": "kisa_sap_re_sol_la",
    "tuning_offset_semitones": 0,
    "notes": [
      { "time": 0.0,  "note": "D#3", "duration": 0.35, "solfege": "do" },
      { "time": 0.35, "note": "E3",  "duration": 0.35, "solfege": "re" },
      { "time": 0.7,  "note": "E3",  "duration": 0.35, "solfege": "re" },
      { "time": 1.05, "note": "E3",  "duration": 0.35, "solfege": "re" },
      { "time": 1.4,  "note": "D#3", "duration": 0.35, "solfege": "do" },
      { "time": 1.75, "note": "E3",  "duration": 0.35, "solfege": "re" },
      { "time": 2.1,  "note": "C4",  "duration": 0.35, "solfege": "si" },
      { "time": 2.45, "note": "D#3", "duration": 0.35, "solfege": "do" },
      { "time": 2.8,  "note": "C4",  "duration": 0.35, "solfege": "si" },
      { "time": 3.15, "note": "B3",  "duration": 0.35, "solfege": "la" },
      { "time": 3.5,  "note": "C4",  "duration": 0.35, "solfege": "si" },
      { "time": 3.85, "note": "B3",  "duration": 0.35, "solfege": "la" },
      { "time": 4.2,  "note": "B3",  "duration": 0.7,  "solfege": "la" },
      { "time": 4.9,  "note": "D#3", "duration": 0.35, "solfege": "do" },
      { "time": 5.25, "note": "C4",  "duration": 0.35, "solfege": "si" },
      { "time": 5.6,  "note": "B3",  "duration": 0.35, "solfege": "la" },
      { "time": 5.95, "note": "C4",  "duration": 0.35, "solfege": "si" },
      { "time": 6.3,  "note": "B3",  "duration": 0.35, "solfege": "la" },
      { "time": 6.65, "note": "B3",  "duration": 0.35, "solfege": "la" },
      { "time": 7.0,  "note": "C4",  "duration": 0.35, "solfege": "si" },
      { "time": 7.35, "note": "D#3", "duration": 0.35, "solfege": "do" },
      { "time": 7.7,  "note": "C4",  "duration": 0.35, "solfege": "si" },
      { "time": 8.05, "note": "C4",  "duration": 0.35, "solfege": "si" },
      { "time": 8.4,  "note": "B3",  "duration": 0.35, "solfege": "la" },
      { "time": 8.75, "note": "C4",  "duration": 0.35, "solfege": "si" },
      { "time": 9.1,  "note": "B3",  "duration": 0.35, "solfege": "la" },
      { "time": 9.45, "note": "C4",  "duration": 0.35, "solfege": "si" },
      { "time": 9.8,  "note": "B3",  "duration": 0.35, "solfege": "la" },
      { "time": 10.15,"note": "D#3", "duration": 0.35, "solfege": "do" },
      { "time": 10.5, "note": "E3",  "duration": 0.35, "solfege": "re" },
      { "time": 10.85,"note": "E3",  "duration": 0.35, "solfege": "re" },
      { "time": 11.2, "note": "E3",  "duration": 0.35, "solfege": "re" },
      { "time": 11.55,"note": "D#3", "duration": 0.35, "solfege": "do" },
      { "time": 11.9, "note": "E3",  "duration": 0.35, "solfege": "re" },
      { "time": 12.25,"note": "C4",  "duration": 0.35, "solfege": "si" },
      { "time": 12.6, "note": "D#3", "duration": 0.35, "solfege": "do" },
      { "time": 12.95,"note": "C4",  "duration": 0.35, "solfege": "si" },
      { "time": 13.3, "note": "B3",  "duration": 0.35, "solfege": "la" },
      { "time": 13.65,"note": "C4",  "duration": 0.35, "solfege": "si" },
      { "time": 14.0, "note": "B3",  "duration": 0.35, "solfege": "la" },
      { "time": 14.35,"note": "B3",  "duration": 0.7,  "solfege": "la" },
      { "time": 15.05,"note": "D#3", "duration": 0.35, "solfege": "do" },
      { "time": 15.4, "note": "E3",  "duration": 0.35, "solfege": "re" },
      { "time": 15.75,"note": "E3",  "duration": 0.35, "solfege": "re" },
      { "time": 16.1, "note": "E3",  "duration": 0.35, "solfege": "re" },
      { "time": 16.45,"note": "F#3", "duration": 0.35, "solfege": "mi" },
      { "time": 16.8, "note": "E3",  "duration": 0.35, "solfege": "re" },
      { "time": 17.15,"note": "E3",  "duration": 0.35, "solfege": "re" },
      { "time": 17.5, "note": "E3",  "duration": 0.35, "solfege": "re" },
      { "time": 17.85,"note": "F#3", "duration": 0.35, "solfege": "mi" },
      { "time": 18.2, "note": "E3",  "duration": 0.35, "solfege": "re" },
      { "time": 18.55,"note": "F#3", "duration": 0.35, "solfege": "mi" },
      { "time": 18.9, "note": "D#3", "duration": 0.35, "solfege": "do" },
      { "time": 19.25,"note": "E3",  "duration": 0.35, "solfege": "re" },
      { "time": 19.6, "note": "D#3", "duration": 0.35, "solfege": "do" },
      { "time": 19.95,"note": "E3",  "duration": 0.35, "solfege": "re" },
      { "time": 20.3, "note": "C4",  "duration": 0.35, "solfege": "si" },
      { "time": 20.65,"note": "C4",  "duration": 0.35, "solfege": "si" },
      { "time": 21.0, "note": "B3",  "duration": 0.35, "solfege": "la" },
      { "time": 21.35,"note": "C4",  "duration": 0.35, "solfege": "si" },
      { "time": 21.7, "note": "B3",  "duration": 0.35, "solfege": "la" },
      { "time": 22.05,"note": "B3",  "duration": 0.7,  "solfege": "la" },
      { "time": 22.75,"note": "D#3", "duration": 0.35, "solfege": "do" },
      { "time": 23.1, "note": "E3",  "duration": 0.35, "solfege": "re" },
      { "time": 23.45,"note": "E3",  "duration": 0.35, "solfege": "re" },
      { "time": 23.8, "note": "E3",  "duration": 0.35, "solfege": "re" },
      { "time": 24.15,"note": "D#3", "duration": 0.35, "solfege": "do" },
      { "time": 24.5, "note": "E3",  "duration": 0.35, "solfege": "re" },
      { "time": 24.85,"note": "C4",  "duration": 0.35, "solfege": "si" },
      { "time": 25.2, "note": "D#3", "duration": 0.35, "solfege": "do" },
      { "time": 25.55,"note": "C4",  "duration": 0.35, "solfege": "si" },
      { "time": 25.9, "note": "B3",  "duration": 0.35, "solfege": "la" },
      { "time": 26.25,"note": "C4",  "duration": 0.35, "solfege": "si" },
      { "time": 26.6, "note": "B3",  "duration": 0.35, "solfege": "la" },
      { "time": 26.95,"note": "B3",  "duration": 0.35, "solfege": "la" },
      { "time": 27.3, "note": "C4",  "duration": 0.35, "solfege": "si" },
      { "time": 27.65,"note": "D#3", "duration": 0.35, "solfege": "do" },
      { "time": 28.0, "note": "C4",  "duration": 0.35, "solfege": "si" },
      { "time": 28.35,"note": "C4",  "duration": 0.35, "solfege": "si" },
      { "time": 28.7, "note": "B3",  "duration": 0.35, "solfege": "la" },
      { "time": 29.05,"note": "C4",  "duration": 0.35, "solfege": "si" },
      { "time": 29.4, "note": "B3",  "duration": 0.35, "solfege": "la" },
      { "time": 29.75,"note": "C4",  "duration": 0.35, "solfege": "si" },
      { "time": 30.1, "note": "B3",  "duration": 0.35, "solfege": "la" },
      { "time": 30.45,"note": "B3",  "duration": 0.35, "solfege": "la" },
      { "time": 30.8, "note": "D#3", "duration": 0.35, "solfege": "do" },
      { "time": 31.15,"note": "E3",  "duration": 0.35, "solfege": "re" },
      { "time": 31.5, "note": "E3",  "duration": 0.35, "solfege": "re" },
      { "time": 31.85,"note": "E3",  "duration": 0.35, "solfege": "re" },
      { "time": 32.2, "note": "D#3", "duration": 0.35, "solfege": "do" },
      { "time": 32.55,"note": "E3",  "duration": 0.35, "solfege": "re" },
      { "time": 32.9, "note": "C4",  "duration": 0.35, "solfege": "si" },
      { "time": 33.25,"note": "D#3", "duration": 0.35, "solfege": "do" },
      { "time": 33.6, "note": "C4",  "duration": 0.35, "solfege": "si" },
      { "time": 33.95,"note": "B3",  "duration": 0.35, "solfege": "la" },
      { "time": 34.3, "note": "C4",  "duration": 0.35, "solfege": "si" },
      { "time": 34.65,"note": "B3",  "duration": 0.35, "solfege": "la" },
      { "time": 35.0, "note": "B3",  "duration": 0.35, "solfege": "la" },
      { "time": 35.35,"note": "C4",  "duration": 0.35, "solfege": "si" },
      { "time": 35.7, "note": "D#3", "duration": 0.35, "solfege": "do" },
      { "time": 36.05,"note": "C4",  "duration": 0.35, "solfege": "si" },
      { "time": 36.4, "note": "C4",  "duration": 0.35, "solfege": "si" },
      { "time": 36.75,"note": "B3",  "duration": 0.35, "solfege": "la" },
      { "time": 37.1, "note": "C4",  "duration": 0.35, "solfege": "si" },
      { "time": 37.45,"note": "B3",  "duration": 0.35, "solfege": "la" },
      { "time": 37.8, "note": "C4",  "duration": 0.35, "solfege": "si" },
      { "time": 38.15,"note": "B3",  "duration": 0.35, "solfege": "la" },
      { "time": 38.5, "note": "B3",  "duration": 0.35, "solfege": "la" },
      { "time": 38.85,"note": "D#3", "duration": 0.35, "solfege": "do" },
      { "time": 39.2, "note": "E3",  "duration": 0.35, "solfege": "re" },
      { "time": 39.55,"note": "E3",  "duration": 0.35, "solfege": "re" },
      { "time": 39.9, "note": "E3",  "duration": 0.35, "solfege": "re" },
      { "time": 40.25,"note": "D#3", "duration": 0.35, "solfege": "do" },
      { "time": 40.6, "note": "E3",  "duration": 0.35, "solfege": "re" },
      { "time": 40.95,"note": "C4",  "duration": 0.35, "solfege": "si" },
      { "time": 41.3, "note": "D#3", "duration": 0.35, "solfege": "do" },
      { "time": 41.65,"note": "C4",  "duration": 0.35, "solfege": "si" },
      { "time": 42.0, "note": "B3",  "duration": 0.35, "solfege": "la" },
      { "time": 42.35,"note": "C4",  "duration": 0.35, "solfege": "si" },
      { "time": 42.7, "note": "B3",  "duration": 0.35, "solfege": "la" },
      { "time": 43.05,"note": "B3",  "duration": 0.35, "solfege": "la" },
      { "time": 43.4, "note": "B3",  "duration": 1.0,  "solfege": "la" },
      { "time": 44.4, "note": "D#3", "duration": 0.35, "solfege": "do" },
      { "time": 44.75,"note": "E3",  "duration": 0.35, "solfege": "re" },
      { "time": 45.1, "note": "E3",  "duration": 0.35, "solfege": "re" },
      { "time": 45.45,"note": "E3",  "duration": 0.35, "solfege": "re" },
      { "time": 45.8, "note": "D#3", "duration": 0.35, "solfege": "do" },
      { "time": 46.15,"note": "E3",  "duration": 0.35, "solfege": "re" },
      { "time": 46.5, "note": "C4",  "duration": 0.35, "solfege": "si" },
      { "time": 46.85,"note": "D#3", "duration": 0.35, "solfege": "do" },
      { "time": 47.2, "note": "C4",  "duration": 0.35, "solfege": "si" },
      { "time": 47.55,"note": "B3",  "duration": 0.35, "solfege": "la" },
      { "time": 47.9, "note": "C4",  "duration": 0.35, "solfege": "si" },
      { "time": 48.25,"note": "B3",  "duration": 0.35, "solfege": "la" },
      { "time": 48.6, "note": "B3",  "duration": 1.0,  "solfege": "la" }
    ],
    "makam": "hicaz",
    "total_duration_sec": 49.6
  },
  {
    "id": "urfanin-etraf-demo",
    "title": "Urfanın Etrafı - Demo",
    "artist": "Anonim",
    "expected_bpm": 85,
    "description": "Kısa test dizisi. Kısa sap Re-Sol-La akort düzeni.",
    "tuning": "kisa_sap_re_sol_la",
    "tuning_offset_semitones": 0,
    "notes": [
      { "time": 0.0,  "note": "D#3", "duration": 0.35, "solfege": "do", "line": 1 },
      { "time": 0.35, "note": "E3",  "duration": 0.35, "solfege": "re",  "line": 1 },
      { "time": 0.7,  "note": "E3",  "duration": 0.35, "solfege": "re",  "line": 1 },
      { "time": 1.05, "note": "E3",  "duration": 0.35, "solfege": "re",  "line": 1 },
      { "time": 1.4,  "note": "D#3", "duration": 0.35, "solfege": "do", "line": 1 },
      { "time": 1.75, "note": "E3",  "duration": 0.35, "solfege": "re",  "line": 1 },
      { "time": 2.1,  "note": "C4",  "duration": 0.35, "solfege": "si",  "line": 1 },
      { "time": 2.45, "note": "D#3", "duration": 0.35, "solfege": "do", "line": 1 },
      { "time": 2.8,  "note": "C4",  "duration": 0.35, "solfege": "si",  "line": 1 },
      { "time": 3.15, "note": "B3",  "duration": 0.35, "solfege": "la",  "line": 1 },
      { "time": 3.5,  "note": "C4",  "duration": 0.35, "solfege": "si",  "line": 1 },
      { "time": 3.85, "note": "B3",  "duration": 0.35, "solfege": "la",  "line": 1 },
      { "time": 4.2,  "note": "B3",  "duration": 0.7,  "solfege": "la",  "line": 1 },
      { "time": 4.9,  "note": "D#3", "duration": 0.35, "solfege": "do", "line": 2 },
      { "time": 5.25, "note": "C4",  "duration": 0.35, "solfege": "si",  "line": 2 },
      { "time": 5.6,  "note": "B3",  "duration": 0.35, "solfege": "la",  "line": 2 },
      { "time": 5.95, "note": "C4",  "duration": 0.35, "solfege": "si",  "line": 2 },
      { "time": 6.3,  "note": "B3",  "duration": 0.35, "solfege": "la",  "line": 2 },
      { "time": 6.65, "note": "B3",  "duration": 0.35, "solfege": "la",  "line": 2 },
      { "time": 7.0,  "note": "C4",  "duration": 0.35, "solfege": "si",  "line": 2 },
      { "time": 7.35, "note": "D#3", "duration": 0.35, "solfege": "do", "line": 2 },
      { "time": 7.7,  "note": "C4",  "duration": 0.35, "solfege": "si",  "line": 2 },
      { "time": 8.05, "note": "C4",  "duration": 0.35, "solfege": "si",  "line": 2 },
      { "time": 8.4,  "note": "B3",  "duration": 0.35, "solfege": "la",  "line": 2 },
      { "time": 8.75, "note": "C4",  "duration": 0.35, "solfege": "si",  "line": 2 },
      { "time": 9.1,  "note": "B3",  "duration": 1.0,  "solfege": "la",  "line": 2 }
    ],
    "makam": "hicaz",
    "total_duration_sec": 10.1
  }
]